okta_saml-0.0.2.dist-info/licenses/LICENSE
oktasamlcli/__init__.py
oktasamlcli/okta_auth.py
oktasamlcli/okta_auth_config.py
oktasamlcli/okta_samlcli.py
oktasamlcli/saml_auth.py
oktasamlcli/version.py
okta_saml-0.0.2.dist-info/METADATA
okta_saml-0.0.2.dist-info/WHEEL
okta_saml-0.0.2.dist-info/entry_points.txt
okta_saml-0.0.2.dist-info/top_level.txt
okta_saml-0.0.2.dist-info/RECORD
