Metadata-Version: 2.4
Name: okta-saml
Version: 0.0.2
Summary: Utility to obtain saml api jwt from OKTA
Author-email: Mike Oshea <oshea00@gmail.com>
Requires-Python: >=3.11
License-File: LICENSE
Requires-Dist: requests>=2.32.3
Requires-Dist: click>=8.0
Requires-Dist: beautifulsoup4>=4.12.0
Requires-Dist: validators>=0.22.0
Dynamic: license-file
